coloredstrings/__init__.py
coloredstrings/__main__.py
coloredstrings/ansi_conversions.py
coloredstrings/color_support.py
coloredstrings/logger.py
coloredstrings/py.typed
coloredstrings/style_builder.py
coloredstrings/stylize.py
coloredstrings/types.py
coloredstrings/utils.py
coloredstrings-3.3.0.dist-info/licenses/LICENSE
coloredstrings-3.3.0.dist-info/WHEEL
coloredstrings-3.3.0.dist-info/METADATA
coloredstrings-3.3.0.dist-info/RECORD
