Metadata-Version: 2.4
Name: coloredstrings
Version: 3.3.0
Summary: Colorize Different.
Keywords: ansi,color,colour,crossplatform,terminal,text
Author: samedit66
Author-email: samedit66 <samedit66@yandex.ru>
License-File: LICENSE
Classifier: Development Status :: 5 - Production/Stable
Classifier: Environment :: Console
Classifier: Intended Audience :: Developers
Classifier: License :: OSI Approved :: Apache Software License
Classifier: Operating System :: OS Independent
Classifier: Programming Language :: Python
Classifier: Programming Language :: Python :: 3
Classifier: Programming Language :: Python :: 3.9
Classifier: Programming Language :: Python :: 3.10
Classifier: Programming Language :: Python :: 3.11
Classifier: Programming Language :: Python :: 3.12
Classifier: Programming Language :: Python :: 3.13
Classifier: Programming Language :: Python :: 3.14
Classifier: Programming Language :: Python :: Implementation :: CPython
Classifier: Topic :: Terminals
Classifier: Topic :: Software Development :: Libraries
Maintainer: samedit66
Maintainer-email: samedit66 <samedit66@yandex.ru>
Requires-Python: >=3.9
Project-URL: Bug Tracker, https://github.com/samedit66/coloredstrings/issues
Project-URL: Changelog, https://github.com/samedit66/coloredstrings/releases
Project-URL: Documentation, https://github.com/samedit66/coloredstrings#readme
Project-URL: Homepage, https://github.com/samedit66/coloredstrings
Project-URL: Repository, https://github.com/samedit66/coloredstrings
